LICENSE
README.rst
setup.py
PRTGAPI/PRTGAPI.py
PRTGAPI/__init__.py
PRTGAPI.egg-info/PKG-INFO
PRTGAPI.egg-info/SOURCES.txt
PRTGAPI.egg-info/dependency_links.txt
PRTGAPI.egg-info/top_level.txt