Metadata-Version: 2.1
Name: PRTGAPI
Version: 1.3
Summary: A package meant to make interfacing with the PRTG API more simple.
Home-page: https://github.com/The-Captain8/PRTG-API
Author: The-Captain8
Author-email: 
License: https://github.com/The-Captain8/PRTG-API/blob/main/LICENSE
License-File: LICENSE
